README.rst
setup.py
hitchat.egg-info/PKG-INFO
hitchat.egg-info/SOURCES.txt
hitchat.egg-info/dependency_links.txt
hitchat.egg-info/requires.txt
hitchat.egg-info/top_level.txt
itchat/__init__.py
itchat/config.py
itchat/content.py
itchat/core.py
itchat/log.py
itchat/returnvalues.py
itchat/utils.py
itchat/components/__init__.py
itchat/components/contact.py
itchat/components/hotreload.py
itchat/components/login.py
itchat/components/messages.py
itchat/components/register.py
itchat/storage/__init__.py
itchat/storage/messagequeue.py
itchat/storage/templates.py