Metadata-Version: 1.1
Name: hitchat
Version: 1.0
Summary: base on itchat ,modify some features
Home-page: https://github.com/littlecodersh/ItChat
Author: rain0day
Author-email: 251280920@qq.com
License: MIT
Keywords: wechat itchat api robot weixin personal extend
Platform: UNKNOWN
Classifier: Development Status :: 3 - Alpha
Classifier: Intended Audience :: Developers
Classifier: Topic :: Software Development :: Libraries :: Python Modules
Classifier: License :: OSI Approved :: MIT License
Classifier: Programming Language :: Python :: 2
Classifier: Programming Language :: Python :: 2.6
Classifier: Programming Language :: Python :: 2.7
